bird_cloud_gnn/__init__.py
bird_cloud_gnn/callback.py
bird_cloud_gnn/cross_validation.py
bird_cloud_gnn/early_stopper.py
bird_cloud_gnn/fake.py
bird_cloud_gnn/gnn_model.py
bird_cloud_gnn/radar_dataset.py
bird_cloud_gnn-0.1.0.dist-info/LICENSE
bird_cloud_gnn-0.1.0.dist-info/METADATA
bird_cloud_gnn-0.1.0.dist-info/NOTICE
bird_cloud_gnn-0.1.0.dist-info/WHEEL
bird_cloud_gnn-0.1.0.dist-info/top_level.txt
bird_cloud_gnn-0.1.0.dist-info/RECORD
